jsonTXeditor/__init__.py
jsonTXeditor/__main__.py
jsonTXeditor/json_tx_editor.py
jsontxeditor-0.1.0.dist-info/WHEEL
jsontxeditor-0.1.0.dist-info/METADATA
jsontxeditor-0.1.0.dist-info/RECORD
