Metadata-Version: 2.1
Name: jsontxeditor
Version: 0.1.0
Summary: a tool for editing JSON-formatted transcriptions files
License: MIT
Author: David Flood
Author-email: davidfloodii@gmail.com
Requires-Python: >=3.8,<4.0
Classifier: License :: OSI Approved :: MIT License
Classifier: Programming Language :: Python :: 3
Classifier: Programming Language :: Python :: 3.10
Classifier: Programming Language :: Python :: 3.8
Classifier: Programming Language :: Python :: 3.9
Requires-Dist: PySimpleGUI (>=4.57.0,<5.0.0)
